entropiaevents/__init__.py
entropiaevents/__main__.py
entropiaevents-1.1.0.dist-info/LICENSE
entropiaevents-1.1.0.dist-info/METADATA
entropiaevents-1.1.0.dist-info/WHEEL
entropiaevents-1.1.0.dist-info/top_level.txt
entropiaevents-1.1.0.dist-info/RECORD
