Metadata-Version: 2.1
Name: entropiaevents
Version: 1.1.0
Summary: Fetchs events from entropia.de
Home-page: https://github.com/entropia/py-entropiaevents.git
Author: Christian Lölkes
Author-email: christian.loelkes@gmail.com
License: UNKNOWN
Platform: UNKNOWN
Classifier: Programming Language :: Python :: 2
Classifier: License :: OSI Approved :: MIT License
Classifier: Operating System :: OS Independent
Requires-Python: >=2.7
Requires-Dist: obelixtools
